setup.py
amaze/__init__.py
amaze/cache.py
amaze/config.py
amaze/helpers.py
amaze/node.py
amaze/pattern.py
amaze/template.py
amaze/token.py
amaze.egg-info/PKG-INFO
amaze.egg-info/SOURCES.txt
amaze.egg-info/dependency_links.txt
amaze.egg-info/not-zip-safe
amaze.egg-info/top_level.txt