Metadata-Version: 1.0
Name: amaze
Version: 0.0.1
Summary: A lightweight, flexible and pythonic template engine... and my playground.
Home-page: UNKNOWN
Author: Florian Proksch
Author-email: florian.proksch@outlook.com
License: MIT
Platform: UNKNOWN
